starlette_marshal/__init__.py
starlette_marshal/rapidjson.py
starlette_marshal-0.1.0.dist-info/LICENSE
starlette_marshal-0.1.0.dist-info/METADATA
starlette_marshal-0.1.0.dist-info/WHEEL
starlette_marshal-0.1.0.dist-info/top_level.txt
starlette_marshal-0.1.0.dist-info/RECORD
