Metadata-Version: 2.1
Name: starlette-marshal
Version: 0.1.0
Summary: Dynamic JSON support for Starlette
Home-page: https://github.com/xtarlette/starlette-marshal
Author: Xurvan
Author-email: xojtaba@gmail.com
License: Apache License 2.0
Project-URL: Source, https://github.com/xtarlette/starlette-marshal
Project-URL: Tracker, https://github.com/xtarlette/starlette-marshal/issues
Platform: UNKNOWN
Classifier: Development Status :: 3 - Alpha
Classifier: Intended Audience :: Developers
Classifier: Topic :: Software Development
Classifier: License :: OSI Approved :: Apache Software License
Classifier: Programming Language :: Python :: 3
Requires-Python: >=3.8
License-File: LICENSE
Requires-Dist: starlette (>=0.17)
Provides-Extra: rapidjson
Requires-Dist: python-rapidjson (>=1.5) ; extra == 'rapidjson'
